hhnk_threedi_tools/__init__.py
hhnk_threedi_tools/core/__init__.py
hhnk_threedi_tools/core/folder_helpers.py
hhnk_threedi_tools/core/folders.py
hhnk_threedi_tools/core/folders_modelbuilder.py
hhnk_threedi_tools/core/api/__init__.py
hhnk_threedi_tools/core/api/calculation.py
hhnk_threedi_tools/core/api/calculation_gui_class.py
hhnk_threedi_tools/core/api/download_functions.py
hhnk_threedi_tools/core/api/download_gui_class.py
hhnk_threedi_tools/core/checks/__init__.py
hhnk_threedi_tools/core/checks/bank_levels.py
hhnk_threedi_tools/core/checks/grid_result_metadata.py
hhnk_threedi_tools/core/checks/model_state.py
hhnk_threedi_tools/core/checks/one_d_two_d.py
hhnk_threedi_tools/core/checks/zero_d_one_d.py
hhnk_threedi_tools/core/checks/sqlite/__init__.py
hhnk_threedi_tools/core/checks/sqlite/sqlite_main.py
hhnk_threedi_tools/core/checks/sqlite/structure_control.py
hhnk_threedi_tools/core/climate_scenarios/__init__.py
hhnk_threedi_tools/core/climate_scenarios/interpolate_rasters.py
hhnk_threedi_tools/core/climate_scenarios/klimaatsommen_main.py
hhnk_threedi_tools/core/climate_scenarios/klimaatsommen_prep.py
hhnk_threedi_tools/core/climate_scenarios/maskerkaart.py
hhnk_threedi_tools/core/climate_scenarios/maskerkaart_raster.py
hhnk_threedi_tools/core/climate_scenarios/peilgebieden.py
hhnk_threedi_tools/core/climate_scenarios/ruimtekaart.py
hhnk_threedi_tools/core/climate_scenarios/schadekaart.py
hhnk_threedi_tools/core/climate_scenarios/schadekaart_peilgebieden.py
hhnk_threedi_tools/core/result_rasters/__init__.py
hhnk_threedi_tools/core/result_rasters/calculate_raster.py
hhnk_threedi_tools/core/result_rasters/netcdf_to_gridgpkg.py
hhnk_threedi_tools/core/schematisation/__init__.py
hhnk_threedi_tools/core/schematisation/migrate.py
hhnk_threedi_tools/core/schematisation/model_backup.py
hhnk_threedi_tools/core/schematisation/model_splitter.py
hhnk_threedi_tools/core/schematisation/upload.py
hhnk_threedi_tools/external/__init__.py
hhnk_threedi_tools/external/downloader.py
hhnk_threedi_tools-2024.1.dist-info/METADATA
hhnk_threedi_tools-2024.1.dist-info/WHEEL
hhnk_threedi_tools-2024.1.dist-info/top_level.txt
hhnk_threedi_tools-2024.1.dist-info/RECORD
